pytorch_to_tensorflow
